snakemake_executor_plugin_lsf_jobstep/__init__.py
snakemake_executor_plugin_lsf_jobstep-0.1.10.dist-info/LICENSE
snakemake_executor_plugin_lsf_jobstep-0.1.10.dist-info/METADATA
snakemake_executor_plugin_lsf_jobstep-0.1.10.dist-info/WHEEL
snakemake_executor_plugin_lsf_jobstep-0.1.10.dist-info/RECORD
